{
	"miniprogramRoot": "miniprogram/",
	"cloudfunctionRoot": "cloudfunctions/",
	"setting": {
		"urlCheck": true,
		"es6": true,
		"enhance": true,
		"postcss": true,
		"preloadBackgroundData": false,
		"minified": true,
		"newFeature": true,
		"coverView": true,
		"autoAudits": false,
		"showShadowRootInWxmlPanel": true,
		"scopeDataCheck": false,
		"checkInvalidKey": true,
		"checkSiteMap": true,
		"uploadWithSourceMap": true,
		"babelSetting": {
			"ignore": [],
			"disablePlugins": [],
			"outputPath": ""
		}
	},
	"appid": "wx9487505d3a876738",
	"projectname": "healthCode",
	"libVersion": "2.11.0",
	"simulatorType": "wechat",
	"simulatorPluginLibVersion": {},
	"condition": {
		"search": {
			"current": -1,
			"list": []
		},
		"conversation": {
			"current": -1,
			"list": []
		},
		"plugin": {
			"current": -1,
			"list": []
		},
		"game": {
			"list": []
		},
		"gamePlugin": {
			"current": -1,
			"list": []
		},
		"miniprogram": {
			"current": -1,
			"list": [
				{
					"id": 0,
					"name": "pages/form/index",
					"pathName": "pages/form/index",
					"query": "openid=o7CqC4tuyzdJoM-feijSFwmdkIEE",
					"scene": 1011
				},
				{
					"id": -1,
					"name": "pages/QRcode/QRcode",
					"pathName": "pages/QRcode/QRcode",
					"query": "",
					"scene": null
				},
				{
					"id": -1,
					"name": "pages/QRcode/QRcode",
					"pathName": "pages/QRcode/QRcode",
					"query": "",
					"scene": null
				},
				{
					"id": -1,
					"name": "pages/record/record",
					"pathName": "pages/record/record",
					"query": "",
					"scene": null
				},
				{
					"id": 4,
					"name": "pages/index/index",
					"pathName": "pages/index/index",
					"query": "openid=osXMd5IDKmmbNs3d8e",
					"scene": null
				},
				{
					"id": -1,
					"name": "pages/form/form",
					"pathName": "pages/form/form",
					"query": "",
					"scene": null
				},
				{
					"id": -1,
					"name": "pages/aboutUs/aboutUs",
					"pathName": "pages/aboutUs/aboutUs",
					"query": "",
					"scene": null
				},
				{
					"id": -1,
					"name": "pages/mine/mine",
					"pathName": "pages/mine/mine",
					"query": "openid=o7CqC4tuyzdJoM-feijSFwmdkIEE",
					"scene": null
				},
				{
					"id": -1,
					"name": "pages/setting/setting",
					"pathName": "pages/setting/setting",
					"query": "openid=o7CqC4tuyzdJoM-feijSFwmdkIEE",
					"scene": null
				},
				{
					"id": -1,
					"name": "pages/addRecord/addRecord",
					"pathName": "pages/addRecord/addRecord",
					"query": "",
					"scene": null
				},
				{
					"id": -1,
					"name": "pages/subscription/subscription",
					"pathName": "pages/subscription/subscription",
					"scene": null
				}
			]
		}
	}
}